LICENSE
README.md
pvsfunc/__init__.py
pvsfunc/helpers.py
pvsfunc/pd2v.py
pvsfunc/pdebox.py
pvsfunc/pdecimate.py
pvsfunc/pkernel.py
pvsfunc/plwi.py
pvsfunc-4.4.0.dist-info/LICENSE
pvsfunc-4.4.0.dist-info/WHEEL
pvsfunc-4.4.0.dist-info/METADATA
pvsfunc-4.4.0.dist-info/RECORD
