Metadata-Version: 2.1
Name: pvsfunc
Version: 4.4.0
Summary: PHOENiX's compilation of VapourSynth Script's and Functions
Home-page: https://github.com/rlaphoenix/pvsfunc
License: GPL-3.0-or-later
Keywords: python,vapoursynth
Author: PHOENiX
Author-email: rlaphoenix@pm.me
Maintainer: PHOENiX
Maintainer-email: rlaphoenix@pm.me
Requires-Python: >=3.7,<4.0
Classifier: Development Status :: 5 - Production/Stable
Classifier: Intended Audience :: Developers
Classifier: License :: OSI Approved :: GNU General Public License v3 or later (GPLv3+)
Classifier: Natural Language :: English
Classifier: Operating System :: OS Independent
Classifier: Programming Language :: Python :: 3
Classifier: Programming Language :: Python :: 3.10
Classifier: Programming Language :: Python :: 3.7
Classifier: Programming Language :: Python :: 3.8
Classifier: Programming Language :: Python :: 3.9
Classifier: Topic :: Multimedia
Classifier: Topic :: Multimedia :: Video
Classifier: Topic :: Multimedia :: Video :: Conversion
Requires-Dist: more-itertools (>=8.8.0,<9.0.0)
Requires-Dist: pyd2v (>=1.3.0,<2.0.0)
Requires-Dist: pymediainfo (>=5.1.0,<6.0.0)
Project-URL: Documentation, https://github.com/rlaphoenix/pvsfunc
Project-URL: Repository, https://github.com/rlaphoenix/pvsfunc
